vaccineAvailabilityNotifier/__init__.py
vaccineAvailabilityNotifier/__main__.py
vaccineAvailabilityNotifier/client/__init__.py
vaccineAvailabilityNotifier/client/actions.py
vaccineAvailabilityNotifier/client/actionsImpl.py
vaccineAvailabilityNotifier/client/resources.py
vaccineAvailabilityNotifier/commands/__init__.py
vaccineAvailabilityNotifier/commands/router.py
vaccineAvailabilityNotifier/commands/sub_commands/__init__.py
vaccineAvailabilityNotifier/commands/sub_commands/schedule_job_cmd.py
vaccineAvailabilityNotifier/email/__init__.py
vaccineAvailabilityNotifier/email/email_sender.py
vaccineAvailabilityNotifier/processors/__init__.py
vaccineAvailabilityNotifier/processors/district_info_processor.py
vaccineAvailabilityNotifier/processors/process_by_district_id.py
vaccineAvailabilityNotifier/processors/process_by_pincodes.py
vaccineAvailabilityNotifier/processors/state_info_processor.py
vaccineAvailabilityNotifier/processors/jobs/__init__.py
vaccineAvailabilityNotifier/processors/jobs/schedule_job.py
vaccineAvailabilityNotifier/util/__init__.py
vaccineAvailabilityNotifier/util/file_util.py
vaccineAvailabilityNotifier/util/response_processor_utils.py
vaccine_availability_notifier-0.0.20.dist-info/LICENSE
vaccine_availability_notifier-0.0.20.dist-info/METADATA
vaccine_availability_notifier-0.0.20.dist-info/WHEEL
vaccine_availability_notifier-0.0.20.dist-info/entry_points.txt
vaccine_availability_notifier-0.0.20.dist-info/top_level.txt
vaccine_availability_notifier-0.0.20.dist-info/RECORD
