Metadata-Version: 2.1
Name: vaccine-availability-notifier
Version: 0.0.20
Summary: vaccine-availability-notifier
Home-page: UNKNOWN
Author: Nandkishor bhasker
Author-email: bhasker.nandkishor@gmail.com
License: UNKNOWN
Platform: UNKNOWN
Requires-Python: >=3.8
License-File: LICENSE
Requires-Dist: click
Requires-Dist: schedule
Requires-Dist: requests
Requires-Dist: setuptools
Requires-Dist: wheel
Requires-Dist: secure-smtplib
